textunitlib/__init__.py
textunitlib/core.py
textunitlib/lib_functions.py
textunitlib/nlp_handler.py
textunitlib/LinguisticResources/de/contractions/contractions.txt
textunitlib/LinguisticResources/de/functionwords/Abtönungspartikeln (betont) .txt
textunitlib/LinguisticResources/de/functionwords/Abtönungspartikeln (unbetont) .txt
textunitlib/LinguisticResources/de/functionwords/Ausdruckspartikel.txt
textunitlib/LinguisticResources/de/functionwords/Fokuspartikeln.txt
textunitlib/LinguisticResources/de/functionwords/Gradpartikel.txt
textunitlib/LinguisticResources/de/functionwords/Konnektivpartikeln.txt
textunitlib/LinguisticResources/de/functionwords/Partikel - Formen und Beispiele Einfache Erklärung EasyDeutsch.URL
textunitlib/LinguisticResources/de/functionwords/Partikel.URL
textunitlib/LinguisticResources/de/functionwords/Präpositionen.txt
textunitlib/LinguisticResources/de/stopwords/stopwords.txt
textunitlib/LinguisticResources/de/vowels/vowels.txt
textunitlib/LinguisticResources/en/contractions/contractions.txt
textunitlib/LinguisticResources/en/functionwords/all.txt
textunitlib/LinguisticResources/en/functionwords/auxiliary_verbs.txt
textunitlib/LinguisticResources/en/functionwords/conjunctions.txt
textunitlib/LinguisticResources/en/functionwords/determiners.txt
textunitlib/LinguisticResources/en/functionwords/prepositions.txt
textunitlib/LinguisticResources/en/functionwords/pronouns.txt
textunitlib/LinguisticResources/en/functionwords/quantifiers.txt
textunitlib/LinguisticResources/en/stopwords/stopwords.txt
textunitlib/LinguisticResources/en/vowels/vowels.txt
textunitlib/LinguisticResources/independent/punctuation.txt
textunitlib-0.0.1.dist-info/METADATA
textunitlib-0.0.1.dist-info/WHEEL
textunitlib-0.0.1.dist-info/licenses/LICENSE
textunitlib-0.0.1.dist-info/RECORD
