Metadata-Version: 2.4
Name: textunitlib
Version: 0.0.1
Summary: TextUnitLib: A Python library for extracting diverse text units from textual data
Project-URL: Homepage, https://github.com/Halvani/TextUnitLib
Project-URL: Bug Tracker, https://github.com/Halvani/TextUnitLib/issues
Author: Oren Halvani
License-File: LICENSE
Keywords: feature-engineering,feature-extraction,stylometry,text-features,text-units
Classifier: Development Status :: 4 - Beta
Classifier: Intended Audience :: Developers
Classifier: License :: OSI Approved :: MIT License
Classifier: Operating System :: OS Independent
Classifier: Programming Language :: Python :: 3.9
Classifier: Programming Language :: Python :: 3.10
Classifier: Programming Language :: Python :: 3.11
Classifier: Programming Language :: Python :: 3.12
Requires-Python: >=3.9
Requires-Dist: datefinder==0.7.3
Requires-Dist: email-scraper==0.5
Requires-Dist: emoji==2.11.0
Requires-Dist: nltk==3.8.1
Requires-Dist: regex==2024.5.15
Requires-Dist: spacy==3.7.4
Requires-Dist: urlextract==1.9.0
